bsgen/__init__.py
bsgen/generate.py
bsgen/data/bullshit_cn.json
bsgen/data/bullshit_en.json
bsgen/data/bullshit_jp.json
bsgen/data/bullshit_zh.json
bsgen-0.2.2.dist-info/LICENSE
bsgen-0.2.2.dist-info/METADATA
bsgen-0.2.2.dist-info/WHEEL
bsgen-0.2.2.dist-info/entry_points.txt
bsgen-0.2.2.dist-info/top_level.txt
bsgen-0.2.2.dist-info/zip-safe
bsgen-0.2.2.dist-info/RECORD
