Metadata-Version: 2.1
Name: bsgen
Version: 0.2.2
Summary: BullshitGenerator
Home-page: https://github.com/voidful/BullshitGenerator
Author: Voidful
Author-email: voidful.stack@gmail.com
License: UNKNOWN
Platform: UNKNOWN
Requires-Dist: inquirer
